glmtuner/__init__.py
glmtuner/api/__init__.py
glmtuner/api/app.py
glmtuner/api/protocol.py
glmtuner/chat/__init__.py
glmtuner/chat/stream_chat.py
glmtuner/dsets/__init__.py
glmtuner/dsets/collator.py
glmtuner/dsets/loader.py
glmtuner/dsets/preprocess.py
glmtuner/dsets/utils.py
glmtuner/extras/__init__.py
glmtuner/extras/callbacks.py
glmtuner/extras/constants.py
glmtuner/extras/logging.py
glmtuner/extras/misc.py
glmtuner/extras/ploting.py
glmtuner/extras/save_and_load.py
glmtuner/hparams/__init__.py
glmtuner/hparams/data_args.py
glmtuner/hparams/finetuning_args.py
glmtuner/hparams/general_args.py
glmtuner/hparams/generating_args.py
glmtuner/hparams/model_args.py
glmtuner/tuner/__init__.py
glmtuner/tuner/core/__init__.py
glmtuner/tuner/core/adapter.py
glmtuner/tuner/core/loader.py
glmtuner/tuner/core/parser.py
glmtuner/tuner/core/trainer.py
glmtuner/tuner/ppo/__init__.py
glmtuner/tuner/ppo/trainer.py
glmtuner/tuner/ppo/utils.py
glmtuner/tuner/ppo/workflow.py
glmtuner/tuner/rm/__init__.py
glmtuner/tuner/rm/collator.py
glmtuner/tuner/rm/metric.py
glmtuner/tuner/rm/trainer.py
glmtuner/tuner/rm/workflow.py
glmtuner/tuner/sft/__init__.py
glmtuner/tuner/sft/metric.py
glmtuner/tuner/sft/trainer.py
glmtuner/tuner/sft/workflow.py
glmtuner/webui/__init__.py
glmtuner/webui/chat.py
glmtuner/webui/common.py
glmtuner/webui/css.py
glmtuner/webui/interface.py
glmtuner/webui/locales.py
glmtuner/webui/manager.py
glmtuner/webui/runner.py
glmtuner/webui/utils.py
glmtuner/webui/components/__init__.py
glmtuner/webui/components/chatbot.py
glmtuner/webui/components/data.py
glmtuner/webui/components/eval.py
glmtuner/webui/components/export.py
glmtuner/webui/components/infer.py
glmtuner/webui/components/sft.py
glmtuner/webui/components/top.py
glmtuner-0.1.5.dist-info/LICENSE
glmtuner-0.1.5.dist-info/METADATA
glmtuner-0.1.5.dist-info/WHEEL
glmtuner-0.1.5.dist-info/top_level.txt
glmtuner-0.1.5.dist-info/RECORD
