Metadata-Version: 2.1
Name: glmtuner
Version: 0.1.5
Summary: Fine-tuning ChatGLM-6B with PEFT
Home-page: https://github.com/hiyouga/ChatGLM-Efficient-Tuning
Author: hiyouga
Author-email: hiyouga@buaa.edu.cn
License: Apache 2.0 License
Keywords: ChatGLM,LLM,ChatGPT,transformer,pytorch,deep learning
Classifier: Development Status :: 3 - Alpha
Classifier: Intended Audience :: Developers
Classifier: Intended Audience :: Education
Classifier: Intended Audience :: Science/Research
Classifier: License :: OSI Approved :: Apache Software License
Classifier: Operating System :: OS Independent
Classifier: Programming Language :: Python :: 3
Classifier: Programming Language :: Python :: 3.8
Classifier: Programming Language :: Python :: 3.9
Classifier: Programming Language :: Python :: 3.10
Classifier: Topic :: Scientific/Engineering :: Artificial Intelligence
Requires-Python: >=3.8.0
License-File: LICENSE
Requires-Dist: torch (>=1.13.1)
Requires-Dist: transformers (>=4.29.1)
Requires-Dist: datasets (>=2.12.0)
Requires-Dist: accelerate (>=0.21.0)
Requires-Dist: peft (>=0.4.0)
Requires-Dist: trl (>=0.4.7)
Requires-Dist: sentencepiece
Requires-Dist: jieba
Requires-Dist: rouge-chinese
Requires-Dist: nltk
Requires-Dist: gradio (>=3.36.0)
Requires-Dist: uvicorn
Requires-Dist: pydantic (==1.10.11)
Requires-Dist: fastapi (==0.95.1)
Requires-Dist: sse-starlette
Requires-Dist: matplotlib
Requires-Dist: protobuf
Requires-Dist: cpm-kernels
